{
  "controls": [
    {
      "name": "radioGroup",
      "label": "This is a radio",
      "value": {
        "controls": [
          {
            "name": "radio1",
            "label": "One",
            "value": "1",
            "type": "radio",
            "validators": {}
          },
          {
            "name": "radio1",
            "label": "Two",
            "value": "2",
            "type": "radio",
            "validators": {}
          },
          {
            "name": "radio1",
            "label": "Three",
            "value": "3",
            "type": "radio",
            "validators": {}
          }
        ]
      },
      "type": "form",
      "validators": {
        "required": true
      }
    },
    {
      "name": "agreesdsTerms",
      "label": "Another",
      "value": {
        "controls": [
          {
            "name": "yourAge",
            "label": "Whats your age",
            "value": 10,
            "type": "range",
            "options": {
              "min": 0,
              "max": 100,
              "step": 1,
              "icon": "sunny"
            },
            "validators": {}
          },
          {
            "name": "lightDark",
            "label": "Do you like switches?",
            "value": false,
            "type": "switch",
            "validators": {}
          }
        ]
      },
      "type": "form",
      "validators": {}
    },
    {
      "name": "yourAge",
      "label": "Whats your age",
      "value": null,
      "type": "range",
      "options": {
        "min": 0,
        "max": 100,
        "step": 1,
        "icon": "sunny"
      },
      "validators": {}
    },
    {
      "name": "switchesLike",
      "label": "Do you like switches?",
      "value": false,
      "type": "switch",
      "validators": {}
    },
    {
      "name": "fileUpload",
      "label": "Choose file",
      "value": null,
      "type": "file",
      "validators": {}
    },
    {
      "name": "articleText",
      "label": "Write a parahraph",
      "value": "php in tags",
      "type": "article",
      "validators": {}
    },
    {
      "name": "date",
      "label": "Meeting date",
      "value": null,
      "type": "date",
      "validators": {}
    }
  ]
}
